tgedr/dataops/__init__.py
tgedr/dataops/chain.py
tgedr/dataops/etl.py
tgedr/dataops/processor.py
tgedr/dataops/utils_reflection.py
tgedr/dataops/commons/dataset.py
tgedr/dataops/commons/metadata.py
tgedr/dataops/commons/s3_connector.py
tgedr/dataops/commons/utils_fs.py
tgedr/dataops/commons/utils_spark.py
tgedr/dataops/sink/__init__.py
tgedr/dataops/sink/local_fs_file_sink.py
tgedr/dataops/sink/s3_file_sink.py
tgedr/dataops/sink/sink.py
tgedr/dataops/source/__init__.py
tgedr/dataops/source/abstract_s3_file_source.py
tgedr/dataops/source/delta_table_source.py
tgedr/dataops/source/local_delta_table.py
tgedr/dataops/source/local_fs_file_source.py
tgedr/dataops/source/pd_df_s3_source.py
tgedr/dataops/source/s3_delta_table.py
tgedr/dataops/source/s3_file_copy.py
tgedr/dataops/source/s3_file_extended_source.py
tgedr/dataops/source/s3_file_source.py
tgedr/dataops/source/source.py
tgedr/dataops/store/fs_single_partition_parquet.py
tgedr/dataops/store/local_fs_single_partition_parquet.py
tgedr/dataops/store/s3_single_partition_parquet.py
tgedr/dataops/store/spark_delta.py
tgedr/dataops/store/store.py
tgedr/dataops/validation/abs.py
tgedr/dataops/validation/pandas.py
tgedr/dataops/validation/pyspark.py
tgedr_dataops-0.0.37.dist-info/LICENSE
tgedr_dataops-0.0.37.dist-info/METADATA
tgedr_dataops-0.0.37.dist-info/WHEEL
tgedr_dataops-0.0.37.dist-info/top_level.txt
tgedr_dataops-0.0.37.dist-info/RECORD
