Metadata-Version: 2.1
Name: tgedr-dataops
Version: 0.0.37
Summary: data operations related code
Home-page: https://github.com/jtviegas-sandbox/dataops
Author: joao tiago viegas
Author-email: jtviegas@gmail.com
License: Unlicense
Keywords: data engineering mlops ml
Classifier: Development Status :: 3 - Alpha
Classifier: Programming Language :: Python :: 3.10
Requires-Python: >=3.9
License-File: LICENSE
Requires-Dist: pandas ==1.5.3
Requires-Dist: pyarrow ==15.*
Requires-Dist: s3fs ==2024.5.0
Requires-Dist: boto3 ==1.34.106
Requires-Dist: great-expectations ==0.18.10
Requires-Dist: deltalake ~=0.16.4
Requires-Dist: openpyxl ==3.1.2
